idleutils/__init__.py
idleutils/__version__.py
idleutils/test.py
idleutils/urlfetcher/__init__.py
idleutils/urlfetcher/urlfetcher.py
idleutils/urlfetcher/utils/__init__.py
idleutils/urlfetcher/utils/response.py
idleutils/urlfetcher/utils/uncurl.py
idleutils/urlfetcher/utils/utils.py
idleutils-0.4.0.dist-info/LICENSE
idleutils-0.4.0.dist-info/METADATA
idleutils-0.4.0.dist-info/WHEEL
idleutils-0.4.0.dist-info/top_level.txt
idleutils-0.4.0.dist-info/RECORD
